LICENSE
MANIFEST.in
README.md
openembedding_setup.py
setup.py
openembedding/__init__.py
openembedding/libcexb_pack.so
openembedding.egg-info/PKG-INFO
openembedding.egg-info/SOURCES.txt
openembedding.egg-info/dependency_links.txt
openembedding.egg-info/requires.txt
openembedding.egg-info/top_level.txt
openembedding/client/Communication.cpp
openembedding/client/Communication.h
openembedding/client/Connection.cpp
openembedding/client/Connection.h
openembedding/client/EmbeddingVariableHandle.cpp
openembedding/client/EmbeddingVariableHandle.h
openembedding/client/EnvConfig.cpp
openembedding/client/EnvConfig.h
openembedding/client/Model.cpp
openembedding/client/Model.h
openembedding/client/ModelController.cpp
openembedding/client/ModelController.h
openembedding/client/ObjectPool.h
openembedding/client/WorkerContext.cpp
openembedding/client/WorkerContext.h
openembedding/entry/c_api.cc
openembedding/entry/c_api.h
openembedding/entry/c_api_ha_test.cpp
openembedding/entry/c_api_test.cpp
openembedding/entry/c_api_test.h
openembedding/entry/controller.cc
openembedding/entry/masterd.cc
openembedding/entry/pmem_c_api_test.cpp
openembedding/entry/py_api.cc
openembedding/entry/server.cc
openembedding/server/EmbeddingDumpOperator.cpp
openembedding/server/EmbeddingDumpOperator.h
openembedding/server/EmbeddingInitOperator.cpp
openembedding/server/EmbeddingInitOperator.h
openembedding/server/EmbeddingLoadOperator.cpp
openembedding/server/EmbeddingLoadOperator.h
openembedding/server/EmbeddingPullOperator.cpp
openembedding/server/EmbeddingPullOperator.h
openembedding/server/EmbeddingPushOperator.cpp
openembedding/server/EmbeddingPushOperator.h
openembedding/server/EmbeddingRestoreOperator.cpp
openembedding/server/EmbeddingRestoreOperator.h
openembedding/server/EmbeddingShardFile.h
openembedding/server/EmbeddingStorage.h
openembedding/server/EmbeddingStoreOperator.cpp
openembedding/server/EmbeddingStoreOperator.h
openembedding/server/RpcView.h
openembedding/tensorflow/Prefetch.h
openembedding/tensorflow/ThreadPool.h
openembedding/tensorflow/__init__.py
openembedding/tensorflow/exb.py
openembedding/tensorflow/exb_ops.cpp
openembedding/tensorflow/../libcexb_pack.so
