Metadata-Version: 2.1
Name: openembedding
Version: 0.1.2
Summary: Distributed framework to accelerate training and support serving.
Home-page: https://github.com/4paradigm/OpenEmbedding
Author: 4paradigm
Author-email: opensource@4paradigm.com
License: UNKNOWN
Keywords: deep learning,tensorflow,keras,AI
Platform: UNKNOWN
Classifier: Programming Language :: Python :: 3
Classifier: Development Status :: 2 - Pre-Alpha
Classifier: Operating System :: POSIX :: Linux
Classifier: License :: OSI Approved :: Apache Software License
Requires-Python: >=3.6
Provides-Extra: tensorflow
